app/main.py
ithappens/__init__.py
ithappens/card.py
ithappens/create_cards.py
ithappens/exceptions.py
ithappens/utils.py
ithappens/cli/__init__.py
ithappens/images/expansion-logo.png
ithappens/style/fonts/__init__.py
ithappens/style/fonts/manage.py
ithappens/style/fonts/Open_Sans/OFL.txt
"ithappens/style/fonts/Open_Sans/OpenSans-Italic-VariableFont_wdth,wght.ttf"
"ithappens/style/fonts/Open_Sans/OpenSans-VariableFont_wdth,wght.ttf"
ithappens/style/fonts/Open_Sans/README.txt
ithappens/style/styles/__init__.py
ithappens/style/styles/registration.py
ithappens-8.0.2.dist-info/LICENSE
ithappens-8.0.2.dist-info/METADATA
ithappens-8.0.2.dist-info/WHEEL
ithappens-8.0.2.dist-info/entry_points.txt
ithappens-8.0.2.dist-info/top_level.txt
ithappens-8.0.2.dist-info/RECORD
