Metadata-Version: 2.2
Name: ithappens
Version: 8.0.2
Summary: Create your own Shit Happens playing cards!
Author: Siem de Jong
License:                     GNU GENERAL PUBLIC LICENSE
Project-URL: Homepage, https://github.com/siemdejong/ithappens
Project-URL: Bug Tracker, https://github.com/siemdejong/ithappens/issues
Keywords: shit happens,card game,it happens
Classifier: Development Status :: 5 - Production/Stable
Classifier: Framework :: Matplotlib
Classifier: Intended Audience :: Developers
Classifier: Intended Audience :: Other Audience
Classifier: License :: OSI Approved :: GNU General Public License v3 (GPLv3)
Classifier: Programming Language :: Python
Classifier: Programming Language :: Python :: 3
Classifier: Programming Language :: Python :: 3 :: Only
Classifier: Programming Language :: Python :: 3.9
Classifier: Programming Language :: Python :: 3.10
Classifier: Programming Language :: Python :: 3.11
Classifier: Programming Language :: Python :: 3.12
Classifier: Topic :: Games/Entertainment :: Board Games
Classifier: Typing :: Typed
Requires-Python: >=3.9
License-File: LICENSE
Requires-Dist: matplotlib>=3.9.4
Requires-Dist: openpyxl>=3.1.5
Requires-Dist: pandas>=2.2.3
Requires-Dist: pymupdf>=1.25.3
Requires-Dist: pyyaml>=6.0.2
Requires-Dist: streamlit>=1.41.1
Requires-Dist: tqdm>=4.67.1
